repository_orm/__init__.py
repository_orm/adapters/__init__.py
repository_orm/adapters/data/__init__.py
repository_orm/adapters/data/abstract.py
repository_orm/adapters/data/cache.py
repository_orm/adapters/data/fake.py
repository_orm/adapters/data/pypika.py
repository_orm/adapters/data/tinydb.py
repository_orm/adapters/file/__init__.py
repository_orm/adapters/file/abstract.py
repository_orm/adapters/file/local_file.py
repository_orm/config.py
repository_orm/exceptions.py
repository_orm/model.py
repository_orm/py.typed
repository_orm/services.py
repository_orm/version.py
repository_orm-1.3.3.dist-info/WHEEL
repository_orm-1.3.3.dist-info/METADATA
repository_orm-1.3.3.dist-info/licenses/LICENSE
repository_orm-1.3.3.dist-info/RECORD
