Metadata-Version: 2.1
Name: repository-orm
Version: 1.3.3
Summary: Library to ease the implementation of the repository pattern in python projects.
License: GPL-3.0-only
Author-email: Lyz <lyz-code-security-advisories@riseup.net>
Requires-Python: >=3.7
Classifier: Development Status :: 5 - Production/Stable
Classifier: Intended Audience :: Developers
Classifier: License :: OSI Approved :: GNU General Public License v3 (GPLv3)
Classifier: Natural Language :: English
Classifier: Operating System :: POSIX
Classifier: Operating System :: Unix
Classifier: Programming Language :: Python
Classifier: Programming Language :: Python :: 3
Classifier: Programming Language :: Python :: 3.10
Classifier: Programming Language :: Python :: 3.7
Classifier: Programming Language :: Python :: 3.8
Classifier: Programming Language :: Python :: 3.9
Classifier: Topic :: Utilities
Requires-Dist: deepdiff>=5.7.0
Requires-Dist: pydantic>=1.9.0
Requires-Dist: pymysql>=1.0.2
Requires-Dist: pypika>=0.48.8
Requires-Dist: tinydb-serialization>=2.1.0
Requires-Dist: tinydb>=4.6.1
Requires-Dist: yoyo-migrations>=7.3.2
Project-URL: Issues, https://github.com/lyz-code/repository-orm/issues
Project-URL: documentation, https://lyz-code.github.io/repository-orm
Project-URL: homepage, https://github.com/lyz-code/repository-orm
